busdriver/__init__.py
busdriver-0.0.1.dist-info/METADATA
busdriver-0.0.1.dist-info/WHEEL
busdriver-0.0.1.dist-info/top_level.txt
busdriver-0.0.1.dist-info/RECORD
