Metadata-Version: 2.1
Name: busdriver
Version: 0.0.1
Summary: Busdriver API
Home-page: UNKNOWN
Author: Zach Morris
Author-email: zacharymorr@outlook.com
License: UNKNOWN
Platform: UNKNOWN
